{
    "date": "2026-03-19",
    "fetch": {
        "status": "complete",
        "completedAt": "2026-03-19T14:30:00Z",
        "candidateCount": 16,
        "sourcesChecked": 82
    },
    "review": {
        "status": "complete",
        "completedAt": "2026-03-19T14:34:19Z",
        "approved": 10,
        "total": 16
    },
    "build": {
        "status": "in-progress",
        "currentPhase": "upload",
        "startedAt": "2026-03-19T15:10:00Z",
        "completedSubPhases": [
            "study-guides",
            "html",
            "digest",
            "podcast",
            "layout-review",
            "upload",
            "html",
            "digest",
            "podcast",
            "layout-review"
        ]
    },
    "lastError": null
}